ecopystats/__init__.py
ecopystats/distance.py
ecopystats/diversity.py
ecopystats/rarefaction.py
ecopystats-0.1.2.dist-info/licenses/LICENSE
ecopystats-0.1.2.dist-info/METADATA
ecopystats-0.1.2.dist-info/WHEEL
ecopystats-0.1.2.dist-info/top_level.txt
ecopystats-0.1.2.dist-info/RECORD
